x_make_github_clones_x/__init__.py
x_make_github_clones_x/x_cls_make_github_clones_x.py
x_make_github_clones_x-12.0.4.dist-info/METADATA
x_make_github_clones_x-12.0.4.dist-info/WHEEL
x_make_github_clones_x-12.0.4.dist-info/top_level.txt
x_make_github_clones_x-12.0.4.dist-info/RECORD
