Metadata-Version: 2.4
Name: x_make_github_clones_x
Version: 12.0.4
Summary: Makes GitHub repository clones.
Author-email: RRGM of the Primus Pilus Night Watch AI Corporation <eye4357@outlook.com>
License-Expression: MIT
